skytup/__init__.py
skytup/cli.py
skytup/core.py
skytup-0.1.1.dist-info/licenses/LICENSE
skytup-0.1.1.dist-info/METADATA
skytup-0.1.1.dist-info/WHEEL
skytup-0.1.1.dist-info/entry_points.txt
skytup-0.1.1.dist-info/top_level.txt
skytup-0.1.1.dist-info/RECORD
